eXtra_cli/__init__.py
eXtra_cli/app/__init__.py
eXtra_cli/app/main.py
eXtra_cli/app/state.py
eXtra_cli/commands/__init__.py
eXtra_cli/commands/add.py
eXtra_cli/commands/check.py
eXtra_cli/commands/fetch.py
eXtra_cli/commands/info.py
eXtra_cli/commands/init.py
eXtra_cli/commands/install.py
eXtra_cli/commands/offload.py
eXtra_cli/commands/remove.py
eXtra_cli/commands/uninstall.py
eXtra_cli/core/__init__.py
eXtra_cli/core/config.py
eXtra_cli/core/console.py
eXtra_cli/core/file.py
eXtra_cli/core/network.py
eXtra_cli/helpers/__init__.py
eXtra_cli/helpers/app.py
eXtra_cli/helpers/common.py
eXtra_cli/helpers/database.py
eXtra_cli/models/__init__.py
eXtra_cli/models/app.py
eXtra_cli/models/config.py
eXtra_cli/models/container.py
eXtra_cli/models/data.py
eXtra_cli/models/workflow.py
extra_cli-0.2.0.dist-info/entry_points.txt
extra_cli-0.2.0.dist-info/LICENSE
extra_cli-0.2.0.dist-info/METADATA
extra_cli-0.2.0.dist-info/WHEEL
extra_cli-0.2.0.dist-info/RECORD
